practicum/__init__.py
practicum/main.py
my_package_practicum-0.1.0.dist-info/METADATA
my_package_practicum-0.1.0.dist-info/WHEEL
my_package_practicum-0.1.0.dist-info/top_level.txt
my_package_practicum-0.1.0.dist-info/RECORD
